RISCV32I-SingleCycleProcessor.srcs/sources_1/new/RegFile.sv
`timescale 1ns / 1ps
//////////////////////////////////////////////////////////////////////////////////
// Company: 
// Engineer: 
// 
// Create Date: 10/09/2023 12:18:42 AM
// Design Name: 
// Module Name: RegFile
// Project Name: 
// Target Devices: 
// Tool Versions: 
// Description: 
// 
// Dependencies: 
// 
// Revision:
// Revision 0.01 - File Created
// Additional Comments:
// 
//////////////////////////////////////////////////////////////////////////////////


module RegFile
(
    input logic clk,                    // Clock
    input logic [4:0]  read_register_1, // Read Register 1 index
    input logic [4:0]  read_register_2, // Read Register 2 index
    input logic [4:0]  write_register,  // Write Register index
    input logic write_enable,           // Write enable signal
    input logic [31:0] write_data,      // Data to be written
    input logic rst_n,                  // Reset
    output logic [31:0] read_data_1,    // Data read from Register 1
    output logic [31:0] read_data_2     // Data read from Register 2
);

    // Declare an array to store the register values
    logic [31:0] registers [31:0] = '{default: 32'h0};
    integer i;

    // Read data from the registers
    assign read_data_1 = (read_register_1 == 5'b0) ? 32'h0 : registers[read_register_1];
    assign read_data_2 = (read_register_2 == 5'b0) ? 32'h0 : registers[read_register_2];

    // Write data to the registers
    always_ff @(posedge clk) begin
        if (rst_n == 0) begin   // Synchronous active low reset            
            registers = '{default: 32'h0};
        end else if (write_enable) begin
            if (write_register != 5'b0) begin
                registers[write_register] <= write_data;
            end
        end
    end

endmodule

RISCV32I-SingleCycleProcessor.srcs/sim_1/new/RegFile_tb.sv
`timescale 1ns / 1ps
//////////////////////////////////////////////////////////////////////////////////
// Company: 
// Engineer: 
// 
// Create Date: 10/09/2023 07:34:38 AM
// Design Name: 
// Module Name: RegFile_tb
// Project Name: 
// Target Devices: 
// Tool Versions: 
// Description: 
// 
// Dependencies: 
// 
// Revision:
// Revision 0.01 - File Created
// Additional Comments:
// 
//////////////////////////////////////////////////////////////////////////////////


module RegFile_tb;

    // Declare signals for RegFile module
    logic clk;
    logic rst_n;
    logic [4:0] read_register_1, read_register_2, write_register;
    logic write_enable;
    logic [31:0] write_data;
    logic [31:0] read_data_1, read_data_2;

    // Instantiate the RegFile module
    RegFile regfile (
        .clk(clk),
        .rst_n(rst_n),
        .read_register_1(read_register_1),
        .read_register_2(read_register_2),
        .write_register(write_register),
        .write_enable(write_enable),
        .write_data(write_data),
        .read_data_1(read_data_1),
        .read_data_2(read_data_2)
    );

    // Clock signal
    always begin
        clk = 0;
        #5;
        clk = 1;
        #5;
    end

    // Test stimulus
    initial begin
        rst_n = 0; // Reset
        #10 rst_n = 1; // De-assert reset after 10 time units

        #10;
        read_register_1 = 3;

        // Perform a write operation to register 3
        #20;
        write_register = 3;
        write_enable = 1;
        write_data = 32'hABCDEF01;
        #10 write_enable = 0;

        // Perform read operations from registers 1 and 2
        #10;
        read_register_1 = 1;
        read_register_2 = 3;
        #10;

        rst_n = 0;
        #10;
        read_register_2 = 3;
        #10;

        // End simulation
        $finish;
    end

endmodule

RISCV32I-SingleCycleProcessor.sim/sim_1/behav/xsim/dump.vcd
$date
   Mon Oct  9 09:10:51 2023
$end
$version
  2020.2
$end
$timescale
  1ps
$end
$scope module RegFile_tb $end
$var reg 1 ! clk $end
$var reg 1 " rst_n $end
$var reg 5 # read_register_1 [4:0] $end
$var reg 5 $ read_register_2 [4:0] $end
$var reg 5 % write_register [4:0] $end
$var reg 1 & write_enable $end
$var reg 32 ' write_data [31:0] $end
$var reg 32 ( read_data_1 [31:0] $end
$var reg 32 ) read_data_2 [31:0] $end
$scope module regfile $end
$var wire 1 * clk $end
$var wire 5 + read_register_1 [4:0] $end
$var wire 5 , read_register_2 [4:0] $end
$var wire 5 - write_register [4:0] $end
$var wire 1 . write_enable $end
$var wire 32 / write_data [31:0] $end
$var wire 1 0 rst_n $end
$var reg 32 ( read_data_1 [31:0] $end
$var reg 32 ) read_data_2 [31:0] $end
$var integer 32 1 i $end
$upscope $end
$upscope $end
$enddefinitions $end
#0
$dumpvars
0!
0"
bx #
bx $
bx %
x&
bx '
bx (
bx )
0*
bx +
bx ,
bx -
x.
bx /
00
bx 1
$end
#5000
1!
1*
b100000 1
#10000
0!
1"
0*
10
#15000
1!
1*
#20000
0!
b11 #
b0 (
0*
b11 +
#25000
1!
1*
#30000
0!
0*
#35000
1!
1*
#40000
0!
b11 %
1&
b10101011110011011110111100000001 '
0*
b11 -
1.
b10101011110011011110111100000001 /
#45000
1!
b10101011110011011110111100000001 (
bx )
1*
#50000
0!
0&
0*
0.
#55000
1!
1*
#60000
0!
b1 #
b11 $
b0 (
b10101011110011011110111100000001 )
0*
b1 +
b11 ,
#65000
1!
1*
#70000
0!
0"
0*
00
#75000
1!
b0 (
b0 )
1*
b100000 1
#80000
0!
b11 $
0*
#85000
1!
1*
b100000 1
